tobolove_distributions/Binomialdistribution.py
tobolove_distributions/Gaussiandistribution.py
tobolove_distributions/Generaldistribution.py
tobolove_distributions/__init__.py
tobolove_distributions-0.2.dist-info/METADATA
tobolove_distributions-0.2.dist-info/WHEEL
tobolove_distributions-0.2.dist-info/top_level.txt
tobolove_distributions-0.2.dist-info/RECORD
