Metadata-Version: 2.4
Name: tobolove_distributions
Version: 0.2
Summary: Gaussian distributions
Author: Tobias Frei
Dynamic: summary
